lda/__init__.py
lda/_lda.cp310-win_amd64.dll.a
lda/_lda.cp311-win_amd64.dll.a
lda/_lda.cp311-win_amd64.pyd
lda/_lda.pyx
lda/datasets.py
lda/gamma.c
lda/gamma.h
lda/lda.py
lda/tests/__init__.py
lda/tests/reuters.ldac
lda/tests/reuters.titles
lda/tests/reuters.tokens
lda/tests/test_datasets.py
lda/tests/test_lda.py
lda/tests/test_lda_reuters.py
lda/tests/test_lda_sparse.py
lda/tests/test_lda_transform.py
lda/tests/test_utils.py
lda/utils.py
lda-3.0.2.dist-info/LICENSE
lda-3.0.2.dist-info/METADATA
lda-3.0.2.dist-info/WHEEL
lda-3.0.2.dist-info/RECORD
